atacbot/__init__.py
atacbot/atacbot.py
atacbot/ataclib.py
atacbot/telegram_atacbot.py
atacbot-0.1.0.dist-info/AUTHORS.rst
atacbot-0.1.0.dist-info/LICENSE
atacbot-0.1.0.dist-info/METADATA
atacbot-0.1.0.dist-info/WHEEL
atacbot-0.1.0.dist-info/entry_points.txt
atacbot-0.1.0.dist-info/top_level.txt
atacbot-0.1.0.dist-info/RECORD
