Metadata-Version: 2.1
Name: atacbot
Version: 0.1.0
Summary: A telegram bot to query muovi.roma.it
Home-page: https://github.com/flavioelawi/Telegram-atacbot
Author: Flavio Elawi
Author-email: flavio.elawi@gmail.com
License: GNU General Public License v3
Keywords: atacbot
Platform: UNKNOWN
Classifier: Development Status :: 2 - Pre-Alpha
Classifier: Intended Audience :: Developers
Classifier: License :: OSI Approved :: GNU General Public License v3 (GPLv3)
Classifier: Natural Language :: English
Classifier: Programming Language :: Python :: 3.6
Classifier: Programming Language :: Python :: 3.7
Requires-Dist: pyTelegramBotAPI
